{
  "music_main_menu_1": {
    "sounds": [
      {
        "name": "chaotic_minigames:music_main_menu_1",
        "stream": false
      }
    ]
  },
  "chop_chop": {
    "sounds": [
      {
        "name": "chaotic_minigames:chop_chop",
        "stream": false
      }
    ]
  },
  "agile_accelerando": {
    "sounds": [
      {
        "name": "chaotic_minigames:agile_accelerando",
        "stream": false
      }
    ]
  },
  "breakneck_boogie": {
    "sounds": [
      {
        "name": "chaotic_minigames:breakneck_boogie",
        "stream": false
      }
    ]
  }
}